{
  "editor:insert-horizontal-rule": [
    {
      "modifiers": [
        "Mod"
      ],
      "key": "-"
    }
  ],
  "editor:toggle-highlight": [
    {
      "modifiers": [
        "Alt",
        "Mod"
      ],
      "key": "="
    }
  ],
  "editor:insert-mathblock": [
    {
      "modifiers": [
        "Mod"
      ],
      "key": "M"
    }
  ],
  "editor:set-heading-3": [
    {
      "modifiers": [
        "Mod"
      ],
      "key": "ArrowUp"
    }
  ],
  "window:zoom-out": [
    {
      "modifiers": [
        "Mod"
      ],
      "key": "ArrowLeft"
    }
  ],
  "editor:insert-codeblock": [
    {
      "modifiers": [
        "Mod"
      ],
      "key": "Q"
    }
  ]
}